Metadata-Version: 2.1
Name: FastNLP
Version: 0.5.0
Summary: fastNLP: Deep Learning Toolkit for NLP, developed by Fudan FastNLP Team
Home-page: https://github.com/fastnlp/fastNLP
Author: FudanNLP
License: Apache License
Platform: UNKNOWN
Requires-Python: >=3.6
Requires-Dist: numpy (>=1.14.2)
Requires-Dist: torch (>=1.0.0)
Requires-Dist: tqdm (>=4.28.1)
Requires-Dist: nltk (>=3.4.1)
Requires-Dist: prettytable (>=0.7.2)
Requires-Dist: requests
Requires-Dist: spacy
